dolib/__init__.py
dolib/__version__.py
dolib/client.py
dolib/models.py
dolib/managers/__init__.py
dolib/managers/account.py
dolib/managers/actions.py
dolib/managers/base.py
dolib/managers/cdns.py
dolib/managers/certificates.py
dolib/managers/databases.py
dolib/managers/domains.py
dolib/managers/droplets.py
dolib/managers/firewalls.py
dolib/managers/floating_ips.py
dolib/managers/images.py
dolib/managers/invoices.py
dolib/managers/kubernetes.py
dolib/managers/load_balancers.py
dolib/managers/projects.py
dolib/managers/regions.py
dolib/managers/registry.py
dolib/managers/snapshots.py
dolib/managers/ssh_keys.py
dolib/managers/tags.py
dolib/managers/volumes.py
dolib/managers/vpcs.py
dolib-0.2.3.dist-info/LICENSE
dolib-0.2.3.dist-info/METADATA
dolib-0.2.3.dist-info/WHEEL
dolib-0.2.3.dist-info/top_level.txt
dolib-0.2.3.dist-info/RECORD
