Metadata-Version: 2.1
Name: dolib
Version: 0.2.3
Summary: Python library for awesome Digital Ocean API
Home-page: https://github.com/geraxe/dolib
Author: Yury Balandin
Author-email: yuri@balandin.ru
License: MIT
Platform: UNKNOWN
Classifier: Development Status :: 3 - Alpha
Classifier: Environment :: Web Environment
Classifier: Intended Audience :: Developers
Classifier: License :: OSI Approved :: MIT License
Classifier: Operating System :: OS Independent
Classifier: Programming Language :: Python
Classifier: Programming Language :: Python :: 3
Classifier: Programming Language :: Python :: 3 :: Only
Classifier: Programming Language :: Python :: 3.6
Classifier: Programming Language :: Python :: 3.7
Classifier: Programming Language :: Python :: 3.8
Classifier: Programming Language :: Python :: 3.9
Classifier: Topic :: Software Development
Classifier: Topic :: Software Development :: Libraries
Requires-Python: >=3.6
License-File: LICENSE
Requires-Dist: httpx
Requires-Dist: pydantic[email]
Provides-Extra: testing
Requires-Dist: pytest ; extra == 'testing'
Requires-Dist: pytest-asyncio ; extra == 'testing'
Requires-Dist: pytest-cov ; extra == 'testing'
Requires-Dist: pytest-recording ; extra == 'testing'
